[
  {
    "url": "https://nlai.ir",
    "status": 200,
    "ok": true,
    "time": 16141
  },
  {
    "url": "https://niafam.nlai.ir",
    "status": "timeout/ssl",
    "ok": false
  },
  {
    "url": "https://icnl.nlai.ir",
    "status": "timeout/ssl",
    "ok": false
  },
  {
    "url": "https://portals.nlai.ir",
    "status": "timeout/ssl",
    "ok": false
  },
  {
    "url": "https://libs.nlai.ir",
    "status": "timeout/ssl",
    "ok": false
  },
  {
    "url": "https://docs.nlai.ir",
    "status": "timeout/ssl",
    "ok": false
  },
  {
    "url": "https://scripts.nlai.ir",
    "status": "timeout/ssl",
    "ok": false
  },
  {
    "url": "https://mags.nlai.ir",
    "status": 200,
    "ok": true,
    "time": 9285
  },
  {
    "url": "https://opac.nlai.ir",
    "status": 200,
    "ok": true,
    "time": 1123
  },
  {
    "url": "https://sana.nlai.ir",
    "status": 200,
    "ok": true,
    "time": 967
  },
  {
    "url": "https://iranjournals.nlai.ir",
    "status": "timeout/ssl",
    "ok": false
  },
  {
    "url": "https://dl.nlai.ir",
    "status": 200,
    "ok": true,
    "time": 2708
  },
  {
    "url": "https://lms.nlai.ir",
    "status": 200,
    "ok": true,
    "time": 1356
  },
  {
    "url": "https://ari.nlai.ir",
    "status": 200,
    "ok": true,
    "time": 10585
  },
  {
    "url": "https://shafaf.nlai.ir",
    "status": 200,
    "ok": true,
    "time": 5952
  },
  {
    "url": "https://hamiankhati.ir",
    "status": 200,
    "ok": true,
    "time": 2136
  },
  {
    "url": "https://researchfestival.nlai.ir",
    "status": 200,
    "ok": true,
    "time": 1148
  },
  {
    "url": "https://researchfestival14.nlai.ir",
    "status": 200,
    "ok": true,
    "time": 1211
  },
  {
    "url": "https://researchfestival15.nlai.ir",
    "status": 200,
    "ok": true,
    "time": 992
  }
]