[
  {
    "url": "https://nlai.ir",
    "status": 200,
    "ok": true,
    "time": 1802
  },
  {
    "url": "https://niafam.nlai.ir",
    "status": 200,
    "ok": true,
    "time": 5008
  },
  {
    "url": "https://icnl.nlai.ir",
    "status": "timeout/ssl",
    "ok": false
  },
  {
    "url": "https://portals.nlai.ir",
    "status": 200,
    "ok": true,
    "time": 5228
  },
  {
    "url": "https://libs.nlai.ir",
    "status": 200,
    "ok": true,
    "time": 9072
  },
  {
    "url": "https://docs.nlai.ir",
    "status": 200,
    "ok": true,
    "time": 4327
  },
  {
    "url": "https://scripts.nlai.ir",
    "status": 500,
    "ok": false,
    "time": 1159
  },
  {
    "url": "https://mags.nlai.ir",
    "status": 200,
    "ok": true,
    "time": 4017
  },
  {
    "url": "https://opac.nlai.ir",
    "status": 200,
    "ok": true,
    "time": 1139
  },
  {
    "url": "https://sana.nlai.ir",
    "status": 200,
    "ok": true,
    "time": 1210
  },
  {
    "url": "https://iranjournals.nlai.ir",
    "status": "timeout/ssl",
    "ok": false
  },
  {
    "url": "https://dl.nlai.ir",
    "status": 200,
    "ok": true,
    "time": 2703
  },
  {
    "url": "https://lms.nlai.ir",
    "status": 200,
    "ok": true,
    "time": 1544
  },
  {
    "url": "https://ari.nlai.ir",
    "status": 200,
    "ok": true,
    "time": 1391
  },
  {
    "url": "https://shafaf.nlai.ir",
    "status": 200,
    "ok": true,
    "time": 900
  },
  {
    "url": "https://hamiankhati.ir",
    "status": "timeout/ssl",
    "ok": false
  },
  {
    "url": "https://researchfestival.nlai.ir",
    "status": 200,
    "ok": true,
    "time": 1393
  },
  {
    "url": "https://researchfestival14.nlai.ir",
    "status": 200,
    "ok": true,
    "time": 1406
  },
  {
    "url": "https://researchfestival15.nlai.ir",
    "status": 200,
    "ok": true,
    "time": 1674
  }
]